mcp_db/__init__.py
mcp_db/connection_pool.py
mcp_db/db.py
mcp_db/metrics.py
mcp_db/security.py
mcp_db/server.py
mseep_mcp_db_navigator-1.0.3.dist-info/licenses/LICENSE
mseep_mcp_db_navigator-1.0.3.dist-info/METADATA
mseep_mcp_db_navigator-1.0.3.dist-info/WHEEL
mseep_mcp_db_navigator-1.0.3.dist-info/entry_points.txt
mseep_mcp_db_navigator-1.0.3.dist-info/top_level.txt
mseep_mcp_db_navigator-1.0.3.dist-info/RECORD
