Metadata-Version: 2.4
Name: mseep-mcp-db-navigator
Version: 1.0.3
Summary: A powerful MySQL/MariaDB database navigation tool using MCP (Model Control Protocol).
Author-email: mseep <support@skydeck.ai>
License: MIT License
Project-URL: Homepage, https://github.com/yourusername/mcp-db
Requires-Python: >=3.8
License-File: LICENSE
Requires-Dist: fastmcp>=0.1.0
Requires-Dist: mysql-connector-python>=8.0.26
Requires-Dist: pydantic>=2.0.0
Requires-Dist: cryptography>=3.4.7
Requires-Dist: typing-extensions>=4.0.0
Dynamic: license-file
